{"name":"Book a successful accommodation","id":"accommodation;book-a-successful-accommodation","testSteps":[{"number":1,"description":"Example: {city\u003dPopayan}","duration":41277,"startTime":"2023-09-28T10:18:48.335-05:00[America/Bogota]","exception":{"errorType":"org.openqa.selenium.ElementNotInteractableException","message":"element not interactable\n  (Session info: chrome\u003d117.0.5938.92)\nBuild info: version: \u00273.141.59\u0027, revision: \u0027e82be7d358\u0027, time: \u00272018-11-14T08:17:03\u0027\nSystem info: host: \u0027DESKTOP-EBETFGH\u0027, ip: \u0027172.18.1.251\u0027, os.name: \u0027Windows 10\u0027, os.arch: \u0027amd64\u0027, os.version: \u002710.0\u0027, java.version: \u00271.8.0_161\u0027\nDriver info: org.openqa.selenium.chrome.ChromeDriver\nCapabilities {acceptInsecureCerts: false, browserName: chrome, browserVersion: 117.0.5938.92, chrome: {chromedriverVersion: 116.0.5845.96 (1a3918166880..., userDataDir: C:\\Users\\SENA\\AppData\\Local...}, fedcm:accounts: true, goog:chromeOptions: {debuggerAddress: localhost:52066}, javascriptEnabled: true, networkConnectionEnabled: false, pageLoadStrategy: normal, platform: WINDOWS, platformName: WINDOWS, proxy: Proxy(), setWindowRect: true, strictFileInteractability: false, timeouts: {implicit: 0, pageLoad: 300000, script: 30000}, unhandledPromptBehavior: dismiss and notify, webauthn:extension:credBlob: true, webauthn:extension:largeBlob: true, webauthn:extension:minPinLength: true, webauthn:extension:prf: true, webauthn:virtualAuthenticators: true}\nSession ID: f9d8232918fbe3b9cddd0ca8aa875aa6","stackTrace":[{"declaringClass":"com.co.qvision.tasks.SearchAccommodationTasks","methodName":"performAs","fileName":"SearchAccommodationTasks.java","lineNumber":58},{"declaringClass":"co.com.Senasoft.StepsDefinitions.AccommodationStepDefinition","methodName":"heClicksOnTheAccommodationsOption","fileName":"AccommodationStepDefinition.java","lineNumber":53},{"declaringClass":"cucumber.runner.Runner","methodName":"runPickle","fileName":"Runner.java","lineNumber":80}]},"result":"ERROR","precondition":false,"level":0,"children":[{"number":2,"description":"Given the user Enter the website","duration":28952,"startTime":"2023-09-28T10:18:48.481-05:00[America/Bogota]","screenshots":[{"screenshot":"14d7dc973427ebed9fca3ff3b642d33f54ac79722b4abab83681159dddc6f536.png","timeStamp":1695914357433}],"result":"SUCCESS","precondition":false,"level":1,"children":[{"number":3,"description":"User opens the https://www.booking.com/","duration":28465,"startTime":"2023-09-28T10:18:48.957-05:00[America/Bogota]","screenshots":[{"screenshot":"14d7dc973427ebed9fca3ff3b642d33f54ac79722b4abab83681159dddc6f536.png","timeStamp":1695914357421}],"result":"SUCCESS","precondition":false,"level":2}]},{"number":4,"description":"When he clicks on the Accommodations option\r\n| city |\r\n| Popayan |","duration":12171,"startTime":"2023-09-28T10:19:17.434-05:00[America/Bogota]","screenshots":[{"screenshot":"14d7dc973427ebed9fca3ff3b642d33f54ac79722b4abab83681159dddc6f536.png","timeStamp":1695914357438}],"exception":{"errorType":"org.openqa.selenium.ElementNotInteractableException","message":"element not interactable\n  (Session info: chrome\u003d117.0.5938.92)\nBuild info: version: \u00273.141.59\u0027, revision: \u0027e82be7d358\u0027, time: \u00272018-11-14T08:17:03\u0027\nSystem info: host: \u0027DESKTOP-EBETFGH\u0027, ip: \u0027172.18.1.251\u0027, os.name: \u0027Windows 10\u0027, os.arch: \u0027amd64\u0027, os.version: \u002710.0\u0027, java.version: \u00271.8.0_161\u0027\nDriver info: org.openqa.selenium.chrome.ChromeDriver\nCapabilities {acceptInsecureCerts: false, browserName: chrome, browserVersion: 117.0.5938.92, chrome: {chromedriverVersion: 116.0.5845.96 (1a3918166880..., userDataDir: C:\\Users\\SENA\\AppData\\Local...}, fedcm:accounts: true, goog:chromeOptions: {debuggerAddress: localhost:52066}, javascriptEnabled: true, networkConnectionEnabled: false, pageLoadStrategy: normal, platform: WINDOWS, platformName: WINDOWS, proxy: Proxy(), setWindowRect: true, strictFileInteractability: false, timeouts: {implicit: 0, pageLoad: 300000, script: 30000}, unhandledPromptBehavior: dismiss and notify, webauthn:extension:credBlob: true, webauthn:extension:largeBlob: true, webauthn:extension:minPinLength: true, webauthn:extension:prf: true, webauthn:virtualAuthenticators: true}\nSession ID: f9d8232918fbe3b9cddd0ca8aa875aa6","stackTrace":[{"declaringClass":"com.co.qvision.tasks.SearchAccommodationTasks","methodName":"performAs","fileName":"SearchAccommodationTasks.java","lineNumber":58},{"declaringClass":"co.com.Senasoft.StepsDefinitions.AccommodationStepDefinition","methodName":"heClicksOnTheAccommodationsOption","fileName":"AccommodationStepDefinition.java","lineNumber":53},{"declaringClass":"cucumber.runner.Runner","methodName":"runPickle","fileName":"Runner.java","lineNumber":80}]},"result":"ERROR","precondition":false,"level":1,"children":[{"number":5,"description":"User close message","duration":1044,"startTime":"2023-09-28T10:19:17.452-05:00[America/Bogota]","screenshots":[{"screenshot":"14d7dc973427ebed9fca3ff3b642d33f54ac79722b4abab83681159dddc6f536.png","timeStamp":1695914357455},{"screenshot":"8ca3f9a09a829bac2cac2b82d88200a68b73f8da05334d2f55d773502533e351.png","timeStamp":1695914358495}],"result":"SUCCESS","precondition":false,"level":2,"children":[{"number":6,"description":"User clicks on Ignorar mensaje","duration":1016,"startTime":"2023-09-28T10:19:17.476-05:00[America/Bogota]","screenshots":[{"screenshot":"d5edf96ce415258983ddc301dd3a4179c922d80e215b711a7754721f277a207d.png","timeStamp":1695914357904},{"screenshot":"8ca3f9a09a829bac2cac2b82d88200a68b73f8da05334d2f55d773502533e351.png","timeStamp":1695914358492}],"result":"SUCCESS","precondition":false,"level":3}]},{"number":7,"description":"User search accommodation tasks","duration":11093,"startTime":"2023-09-28T10:19:18.503-05:00[America/Bogota]","screenshots":[{"screenshot":"8ca3f9a09a829bac2cac2b82d88200a68b73f8da05334d2f55d773502533e351.png","timeStamp":1695914358505}],"exception":{"errorType":"org.openqa.selenium.ElementNotInteractableException","message":"element not interactable\n  (Session info: chrome\u003d117.0.5938.92)\nBuild info: version: \u00273.141.59\u0027, revision: \u0027e82be7d358\u0027, time: \u00272018-11-14T08:17:03\u0027\nSystem info: host: \u0027DESKTOP-EBETFGH\u0027, ip: \u0027172.18.1.251\u0027, os.name: \u0027Windows 10\u0027, os.arch: \u0027amd64\u0027, os.version: \u002710.0\u0027, java.version: \u00271.8.0_161\u0027\nDriver info: org.openqa.selenium.chrome.ChromeDriver\nCapabilities {acceptInsecureCerts: false, browserName: chrome, browserVersion: 117.0.5938.92, chrome: {chromedriverVersion: 116.0.5845.96 (1a3918166880..., userDataDir: C:\\Users\\SENA\\AppData\\Local...}, fedcm:accounts: true, goog:chromeOptions: {debuggerAddress: localhost:52066}, javascriptEnabled: true, networkConnectionEnabled: false, pageLoadStrategy: normal, platform: WINDOWS, platformName: WINDOWS, proxy: Proxy(), setWindowRect: true, strictFileInteractability: false, timeouts: {implicit: 0, pageLoad: 300000, script: 30000}, unhandledPromptBehavior: dismiss and notify, webauthn:extension:credBlob: true, webauthn:extension:largeBlob: true, webauthn:extension:minPinLength: true, webauthn:extension:prf: true, webauthn:virtualAuthenticators: true}\nSession ID: f9d8232918fbe3b9cddd0ca8aa875aa6","stackTrace":[{"declaringClass":"com.co.qvision.tasks.SearchAccommodationTasks","methodName":"performAs","fileName":"SearchAccommodationTasks.java","lineNumber":58},{"declaringClass":"co.com.Senasoft.StepsDefinitions.AccommodationStepDefinition","methodName":"heClicksOnTheAccommodationsOption","fileName":"AccommodationStepDefinition.java","lineNumber":53},{"declaringClass":"cucumber.runner.Runner","methodName":"runPickle","fileName":"Runner.java","lineNumber":80}]},"result":"ERROR","precondition":false,"level":2,"children":[{"number":8,"description":"User enters \u0027Popayan\u0027 into Escribir lugar de hospedaje","duration":493,"startTime":"2023-09-28T10:19:18.526-05:00[America/Bogota]","screenshots":[{"screenshot":"8ca3f9a09a829bac2cac2b82d88200a68b73f8da05334d2f55d773502533e351.png","timeStamp":1695914358529},{"screenshot":"7f11ffd1c1ecc28844e83cb90fd3f5c4d7122cedd0595eea914accbce263090c.png","timeStamp":1695914359019}],"result":"SUCCESS","precondition":false,"level":3},{"number":9,"description":"User clicks on Añadir fechas de alojamiento","duration":423,"startTime":"2023-09-28T10:19:19.023-05:00[America/Bogota]","screenshots":[{"screenshot":"7f11ffd1c1ecc28844e83cb90fd3f5c4d7122cedd0595eea914accbce263090c.png","timeStamp":1695914359027},{"screenshot":"26605d683c829c15c0c03be21bfa7083a80bcf3e767d1ff5976b7ecbccf000b1.png","timeStamp":1695914359446}],"result":"SUCCESS","precondition":false,"level":3},{"number":10,"description":"User clicks on Añadir fechas de primer chequeo","duration":384,"startTime":"2023-09-28T10:19:19.450-05:00[America/Bogota]","screenshots":[{"screenshot":"26605d683c829c15c0c03be21bfa7083a80bcf3e767d1ff5976b7ecbccf000b1.png","timeStamp":1695914359458},{"screenshot":"c36ef9b3eebe39214e523a94d6311f1cf064800699c4b9347b3aa51a183ddf44.png","timeStamp":1695914359834}],"result":"SUCCESS","precondition":false,"level":3},{"number":11,"description":"User clicks on Añadir fechas de ultimo chequeo","duration":373,"startTime":"2023-09-28T10:19:19.838-05:00[America/Bogota]","screenshots":[{"screenshot":"c36ef9b3eebe39214e523a94d6311f1cf064800699c4b9347b3aa51a183ddf44.png","timeStamp":1695914359841},{"screenshot":"476f794fdbd429456b45a14584becab5712e9cc981f8133d114b3fbd7f710b22.png","timeStamp":1695914360211}],"result":"SUCCESS","precondition":false,"level":3},{"number":12,"description":"User clicks on Añadir fechas de alojamiento","duration":434,"startTime":"2023-09-28T10:19:20.218-05:00[America/Bogota]","screenshots":[{"screenshot":"476f794fdbd429456b45a14584becab5712e9cc981f8133d114b3fbd7f710b22.png","timeStamp":1695914360223},{"screenshot":"60af022e9f4b9211e20fddab7356c42cfecaae816f471ba922cfbdf8c8ff998f.png","timeStamp":1695914360652}],"result":"SUCCESS","precondition":false,"level":3},{"number":13,"description":"User clicks on Agregar personas","duration":381,"startTime":"2023-09-28T10:19:20.657-05:00[America/Bogota]","screenshots":[{"screenshot":"60af022e9f4b9211e20fddab7356c42cfecaae816f471ba922cfbdf8c8ff998f.png","timeStamp":1695914360662},{"screenshot":"335461703dfe6f9e2d4ea0d0edd2089feb8aa469c5c8cae64248e85b1974a0fa.png","timeStamp":1695914361038}],"result":"SUCCESS","precondition":false,"level":3},{"number":14,"description":"User clicks on Agregar Adultos","duration":455,"startTime":"2023-09-28T10:19:21.042-05:00[America/Bogota]","screenshots":[{"screenshot":"335461703dfe6f9e2d4ea0d0edd2089feb8aa469c5c8cae64248e85b1974a0fa.png","timeStamp":1695914361048},{"screenshot":"51988cfd6f9d65b128aaa3b99afdcd23c127c153cc92543806ef7c21d97c204b.png","timeStamp":1695914361497}],"result":"SUCCESS","precondition":false,"level":3},{"number":15,"description":"User clicks on Agregar Niños","duration":503,"startTime":"2023-09-28T10:19:21.503-05:00[America/Bogota]","screenshots":[{"screenshot":"51988cfd6f9d65b128aaa3b99afdcd23c127c153cc92543806ef7c21d97c204b.png","timeStamp":1695914361507},{"screenshot":"9aa09828e7065be59bc05aee75bad13b711e8556d6e75262939d880f066608bb.png","timeStamp":1695914362006}],"result":"SUCCESS","precondition":false,"level":3},{"number":16,"description":"User clicks on Agregar Niños","duration":423,"startTime":"2023-09-28T10:19:22.012-05:00[America/Bogota]","screenshots":[{"screenshot":"9aa09828e7065be59bc05aee75bad13b711e8556d6e75262939d880f066608bb.png","timeStamp":1695914362017},{"screenshot":"5540eb2fec052ff8137e3387bfc308b4926730e5b1c64fe17819023364f2ac1a.png","timeStamp":1695914362435}],"result":"SUCCESS","precondition":false,"level":3},{"number":17,"description":"User clicks on Escojer Cantidad de habitaciones","duration":367,"startTime":"2023-09-28T10:19:22.439-05:00[America/Bogota]","screenshots":[{"screenshot":"5540eb2fec052ff8137e3387bfc308b4926730e5b1c64fe17819023364f2ac1a.png","timeStamp":1695914362442},{"screenshot":"8e0ee82be431f9c0b8099465a632f0faf6513a070787e59f94405557f55d251c.png","timeStamp":1695914362805}],"result":"SUCCESS","precondition":false,"level":3},{"number":18,"description":"User clicks on Agregar Edad de los niños","duration":488,"startTime":"2023-09-28T10:19:22.811-05:00[America/Bogota]","screenshots":[{"screenshot":"8e0ee82be431f9c0b8099465a632f0faf6513a070787e59f94405557f55d251c.png","timeStamp":1695914362816},{"screenshot":"bb5375e6dbb49bc94f3a656edf193daf76b78c579418300b61b41b3dc545c259.png","timeStamp":1695914363299}],"result":"SUCCESS","precondition":false,"level":3},{"number":19,"description":"User clicks on Escojer Edad del niño 1","duration":478,"startTime":"2023-09-28T10:19:23.303-05:00[America/Bogota]","screenshots":[{"screenshot":"bb5375e6dbb49bc94f3a656edf193daf76b78c579418300b61b41b3dc545c259.png","timeStamp":1695914363309},{"screenshot":"100b27b6dd068bfc5eda4ae999408f5745f24916c827afc6443097237610f454.png","timeStamp":1695914363781}],"result":"SUCCESS","precondition":false,"level":3},{"number":20,"description":"User clicks on Agregar Edad de los niños","duration":757,"startTime":"2023-09-28T10:19:25.790-05:00[America/Bogota]","screenshots":[{"screenshot":"100b27b6dd068bfc5eda4ae999408f5745f24916c827afc6443097237610f454.png","timeStamp":1695914366027},{"screenshot":"78795dcabf0ebeed044b5b1b42bb52144eec8db7f7d6368d58aeea5029f5f94c.png","timeStamp":1695914366547}],"result":"SUCCESS","precondition":false,"level":3},{"number":21,"description":"User clicks on Escojer Edad del niño 2","duration":412,"startTime":"2023-09-28T10:19:26.550-05:00[America/Bogota]","screenshots":[{"screenshot":"78795dcabf0ebeed044b5b1b42bb52144eec8db7f7d6368d58aeea5029f5f94c.png","timeStamp":1695914366553},{"screenshot":"78795dcabf0ebeed044b5b1b42bb52144eec8db7f7d6368d58aeea5029f5f94c.png","timeStamp":1695914366962}],"result":"SUCCESS","precondition":false,"level":3},{"number":22,"description":"User clicks on Boton guardar","duration":2628,"startTime":"2023-09-28T10:19:26.965-05:00[America/Bogota]","screenshots":[{"screenshot":"78795dcabf0ebeed044b5b1b42bb52144eec8db7f7d6368d58aeea5029f5f94c.png","timeStamp":1695914366967},{"screenshot":"78795dcabf0ebeed044b5b1b42bb52144eec8db7f7d6368d58aeea5029f5f94c.png","htmlSource":"pagesource3516798903878984542.html.txt","timeStamp":1695914369586}],"exception":{"errorType":"org.openqa.selenium.ElementNotInteractableException","message":"element not interactable\n  (Session info: chrome\u003d117.0.5938.92)\nBuild info: version: \u00273.141.59\u0027, revision: \u0027e82be7d358\u0027, time: \u00272018-11-14T08:17:03\u0027\nSystem info: host: \u0027DESKTOP-EBETFGH\u0027, ip: \u0027172.18.1.251\u0027, os.name: \u0027Windows 10\u0027, os.arch: \u0027amd64\u0027, os.version: \u002710.0\u0027, java.version: \u00271.8.0_161\u0027\nDriver info: org.openqa.selenium.chrome.ChromeDriver\nCapabilities {acceptInsecureCerts: false, browserName: chrome, browserVersion: 117.0.5938.92, chrome: {chromedriverVersion: 116.0.5845.96 (1a3918166880..., userDataDir: C:\\Users\\SENA\\AppData\\Local...}, fedcm:accounts: true, goog:chromeOptions: {debuggerAddress: localhost:52066}, javascriptEnabled: true, networkConnectionEnabled: false, pageLoadStrategy: normal, platform: WINDOWS, platformName: WINDOWS, proxy: Proxy(), setWindowRect: true, strictFileInteractability: false, timeouts: {implicit: 0, pageLoad: 300000, script: 30000}, unhandledPromptBehavior: dismiss and notify, webauthn:extension:credBlob: true, webauthn:extension:largeBlob: true, webauthn:extension:minPinLength: true, webauthn:extension:prf: true, webauthn:virtualAuthenticators: true}\nSession ID: f9d8232918fbe3b9cddd0ca8aa875aa6","stackTrace":[{"declaringClass":"com.co.qvision.tasks.SearchAccommodationTasks","methodName":"performAs","fileName":"SearchAccommodationTasks.java","lineNumber":58},{"declaringClass":"co.com.Senasoft.StepsDefinitions.AccommodationStepDefinition","methodName":"heClicksOnTheAccommodationsOption","fileName":"AccommodationStepDefinition.java","lineNumber":53},{"declaringClass":"cucumber.runner.Runner","methodName":"runPickle","fileName":"Runner.java","lineNumber":80}]},"result":"ERROR","precondition":false,"level":3}]}]}]},{"number":23,"description":"And the search and select one of the results","duration":6,"startTime":"2023-09-28T10:19:29.632-05:00[America/Bogota]","result":"SKIPPED","precondition":false,"level":0},{"number":24,"description":"Then he will have reserved a place of accommodation","duration":3,"startTime":"2023-09-28T10:19:29.640-05:00[America/Bogota]","result":"SKIPPED","precondition":false,"level":0},{"number":25,"description":"Example: {city\u003dCali}","duration":18180,"startTime":"2023-09-28T10:19:30.565-05:00[America/Bogota]","exception":{"errorType":"org.openqa.selenium.ElementNotInteractableException","message":"element not interactable\n  (Session info: chrome\u003d117.0.5938.92)\nBuild info: version: \u00273.141.59\u0027, revision: \u0027e82be7d358\u0027, time: \u00272018-11-14T08:17:03\u0027\nSystem info: host: \u0027DESKTOP-EBETFGH\u0027, ip: \u0027172.18.1.251\u0027, os.name: \u0027Windows 10\u0027, os.arch: \u0027amd64\u0027, os.version: \u002710.0\u0027, java.version: \u00271.8.0_161\u0027\nDriver info: org.openqa.selenium.chrome.ChromeDriver\nCapabilities {acceptInsecureCerts: false, browserName: chrome, browserVersion: 117.0.5938.92, chrome: {chromedriverVersion: 116.0.5845.96 (1a3918166880..., userDataDir: C:\\Users\\SENA\\AppData\\Local...}, fedcm:accounts: true, goog:chromeOptions: {debuggerAddress: localhost:52167}, javascriptEnabled: true, networkConnectionEnabled: false, pageLoadStrategy: normal, platform: WINDOWS, platformName: WINDOWS, proxy: Proxy(), setWindowRect: true, strictFileInteractability: false, timeouts: {implicit: 0, pageLoad: 300000, script: 30000}, unhandledPromptBehavior: dismiss and notify, webauthn:extension:credBlob: true, webauthn:extension:largeBlob: true, webauthn:extension:minPinLength: true, webauthn:extension:prf: true, webauthn:virtualAuthenticators: true}\nSession ID: 5d4da3f9c927a093206d9dec39cd5db6","stackTrace":[{"declaringClass":"com.co.qvision.tasks.SearchAccommodationTasks","methodName":"performAs","fileName":"SearchAccommodationTasks.java","lineNumber":58},{"declaringClass":"co.com.Senasoft.StepsDefinitions.AccommodationStepDefinition","methodName":"heClicksOnTheAccommodationsOption","fileName":"AccommodationStepDefinition.java","lineNumber":53},{"declaringClass":"cucumber.runner.Runner","methodName":"runPickle","fileName":"Runner.java","lineNumber":80}]},"result":"ERROR","precondition":false,"level":0,"children":[{"number":26,"description":"Given the user Enter the website","duration":6620,"startTime":"2023-09-28T10:19:30.576-05:00[America/Bogota]","screenshots":[{"screenshot":"989f21e13931f0f08e51e30483a6ad09829e4bf07357b05a0f4f3b02157cf0c1.png","timeStamp":1695914377195}],"result":"SUCCESS","precondition":false,"level":1,"children":[{"number":27,"description":"User opens the https://www.booking.com/","duration":6611,"startTime":"2023-09-28T10:19:30.581-05:00[America/Bogota]","screenshots":[{"screenshot":"989f21e13931f0f08e51e30483a6ad09829e4bf07357b05a0f4f3b02157cf0c1.png","timeStamp":1695914377192}],"result":"SUCCESS","precondition":false,"level":2}]},{"number":28,"description":"When he clicks on the Accommodations option\r\n| city |\r\n| Cali |","duration":11544,"startTime":"2023-09-28T10:19:37.197-05:00[America/Bogota]","screenshots":[{"screenshot":"989f21e13931f0f08e51e30483a6ad09829e4bf07357b05a0f4f3b02157cf0c1.png","timeStamp":1695914377198}],"exception":{"errorType":"org.openqa.selenium.ElementNotInteractableException","message":"element not interactable\n  (Session info: chrome\u003d117.0.5938.92)\nBuild info: version: \u00273.141.59\u0027, revision: \u0027e82be7d358\u0027, time: \u00272018-11-14T08:17:03\u0027\nSystem info: host: \u0027DESKTOP-EBETFGH\u0027, ip: \u0027172.18.1.251\u0027, os.name: \u0027Windows 10\u0027, os.arch: \u0027amd64\u0027, os.version: \u002710.0\u0027, java.version: \u00271.8.0_161\u0027\nDriver info: org.openqa.selenium.chrome.ChromeDriver\nCapabilities {acceptInsecureCerts: false, browserName: chrome, browserVersion: 117.0.5938.92, chrome: {chromedriverVersion: 116.0.5845.96 (1a3918166880..., userDataDir: C:\\Users\\SENA\\AppData\\Local...}, fedcm:accounts: true, goog:chromeOptions: {debuggerAddress: localhost:52167}, javascriptEnabled: true, networkConnectionEnabled: false, pageLoadStrategy: normal, platform: WINDOWS, platformName: WINDOWS, proxy: Proxy(), setWindowRect: true, strictFileInteractability: false, timeouts: {implicit: 0, pageLoad: 300000, script: 30000}, unhandledPromptBehavior: dismiss and notify, webauthn:extension:credBlob: true, webauthn:extension:largeBlob: true, webauthn:extension:minPinLength: true, webauthn:extension:prf: true, webauthn:virtualAuthenticators: true}\nSession ID: 5d4da3f9c927a093206d9dec39cd5db6","stackTrace":[{"declaringClass":"com.co.qvision.tasks.SearchAccommodationTasks","methodName":"performAs","fileName":"SearchAccommodationTasks.java","lineNumber":58},{"declaringClass":"co.com.Senasoft.StepsDefinitions.AccommodationStepDefinition","methodName":"heClicksOnTheAccommodationsOption","fileName":"AccommodationStepDefinition.java","lineNumber":53},{"declaringClass":"cucumber.runner.Runner","methodName":"runPickle","fileName":"Runner.java","lineNumber":80}]},"result":"ERROR","precondition":false,"level":1,"children":[{"number":29,"description":"User close message","duration":411,"startTime":"2023-09-28T10:19:37.202-05:00[America/Bogota]","screenshots":[{"screenshot":"989f21e13931f0f08e51e30483a6ad09829e4bf07357b05a0f4f3b02157cf0c1.png","timeStamp":1695914377203},{"screenshot":"89a30ce0ac5d6cdda657f3c804e3194dc0368d0f9b827a461d355c21547fe034.png","timeStamp":1695914377613}],"result":"SUCCESS","precondition":false,"level":2,"children":[{"number":30,"description":"User clicks on Ignorar mensaje","duration":403,"startTime":"2023-09-28T10:19:37.207-05:00[America/Bogota]","screenshots":[{"screenshot":"989f21e13931f0f08e51e30483a6ad09829e4bf07357b05a0f4f3b02157cf0c1.png","timeStamp":1695914377210},{"screenshot":"89a30ce0ac5d6cdda657f3c804e3194dc0368d0f9b827a461d355c21547fe034.png","timeStamp":1695914377610}],"result":"SUCCESS","precondition":false,"level":3}]},{"number":31,"description":"User search accommodation tasks","duration":11120,"startTime":"2023-09-28T10:19:37.617-05:00[America/Bogota]","screenshots":[{"screenshot":"89a30ce0ac5d6cdda657f3c804e3194dc0368d0f9b827a461d355c21547fe034.png","timeStamp":1695914377619}],"exception":{"errorType":"org.openqa.selenium.ElementNotInteractableException","message":"element not interactable\n  (Session info: chrome\u003d117.0.5938.92)\nBuild info: version: \u00273.141.59\u0027, revision: \u0027e82be7d358\u0027, time: \u00272018-11-14T08:17:03\u0027\nSystem info: host: \u0027DESKTOP-EBETFGH\u0027, ip: \u0027172.18.1.251\u0027, os.name: \u0027Windows 10\u0027, os.arch: \u0027amd64\u0027, os.version: \u002710.0\u0027, java.version: \u00271.8.0_161\u0027\nDriver info: org.openqa.selenium.chrome.ChromeDriver\nCapabilities {acceptInsecureCerts: false, browserName: chrome, browserVersion: 117.0.5938.92, chrome: {chromedriverVersion: 116.0.5845.96 (1a3918166880..., userDataDir: C:\\Users\\SENA\\AppData\\Local...}, fedcm:accounts: true, goog:chromeOptions: {debuggerAddress: localhost:52167}, javascriptEnabled: true, networkConnectionEnabled: false, pageLoadStrategy: normal, platform: WINDOWS, platformName: WINDOWS, proxy: Proxy(), setWindowRect: true, strictFileInteractability: false, timeouts: {implicit: 0, pageLoad: 300000, script: 30000}, unhandledPromptBehavior: dismiss and notify, webauthn:extension:credBlob: true, webauthn:extension:largeBlob: true, webauthn:extension:minPinLength: true, webauthn:extension:prf: true, webauthn:virtualAuthenticators: true}\nSession ID: 5d4da3f9c927a093206d9dec39cd5db6","stackTrace":[{"declaringClass":"com.co.qvision.tasks.SearchAccommodationTasks","methodName":"performAs","fileName":"SearchAccommodationTasks.java","lineNumber":58},{"declaringClass":"co.com.Senasoft.StepsDefinitions.AccommodationStepDefinition","methodName":"heClicksOnTheAccommodationsOption","fileName":"AccommodationStepDefinition.java","lineNumber":53},{"declaringClass":"cucumber.runner.Runner","methodName":"runPickle","fileName":"Runner.java","lineNumber":80}]},"result":"ERROR","precondition":false,"level":2,"children":[{"number":32,"description":"User enters \u0027Cali\u0027 into Escribir lugar de hospedaje","duration":446,"startTime":"2023-09-28T10:19:37.623-05:00[America/Bogota]","screenshots":[{"screenshot":"89a30ce0ac5d6cdda657f3c804e3194dc0368d0f9b827a461d355c21547fe034.png","timeStamp":1695914377626},{"screenshot":"fefb73e8c7ad58fefd16cd1199103ab5cc281a7f94fe981a50349464ed10a564.png","timeStamp":1695914378069}],"result":"SUCCESS","precondition":false,"level":3},{"number":33,"description":"User clicks on Añadir fechas de alojamiento","duration":332,"startTime":"2023-09-28T10:19:38.073-05:00[America/Bogota]","screenshots":[{"screenshot":"fefb73e8c7ad58fefd16cd1199103ab5cc281a7f94fe981a50349464ed10a564.png","timeStamp":1695914378074},{"screenshot":"392c9478ddd27b090d214b7f583948d256f7dbb96bc553f87fe898e567659628.png","timeStamp":1695914378405}],"result":"SUCCESS","precondition":false,"level":3},{"number":34,"description":"User clicks on Añadir fechas de primer chequeo","duration":461,"startTime":"2023-09-28T10:19:38.409-05:00[America/Bogota]","screenshots":[{"screenshot":"392c9478ddd27b090d214b7f583948d256f7dbb96bc553f87fe898e567659628.png","timeStamp":1695914378414},{"screenshot":"3560a886964e49dc51782c3b916f10ebc94f9248d0ac233ac3e743102ceba4d3.png","timeStamp":1695914378870}],"result":"SUCCESS","precondition":false,"level":3},{"number":35,"description":"User clicks on Añadir fechas de ultimo chequeo","duration":456,"startTime":"2023-09-28T10:19:38.875-05:00[America/Bogota]","screenshots":[{"screenshot":"3560a886964e49dc51782c3b916f10ebc94f9248d0ac233ac3e743102ceba4d3.png","timeStamp":1695914378880},{"screenshot":"17a5dea05ef615b166ab81aedb489586d16264d3b4c2ee51b4b2aea0904cb3ef.png","timeStamp":1695914379331}],"result":"SUCCESS","precondition":false,"level":3},{"number":36,"description":"User clicks on Añadir fechas de alojamiento","duration":438,"startTime":"2023-09-28T10:19:39.336-05:00[America/Bogota]","screenshots":[{"screenshot":"17a5dea05ef615b166ab81aedb489586d16264d3b4c2ee51b4b2aea0904cb3ef.png","timeStamp":1695914379341},{"screenshot":"c362c5271c3dbceb82e7449a3498b65bb6c83ac2041ec97ffda8c76d394c6968.png","timeStamp":1695914379774}],"result":"SUCCESS","precondition":false,"level":3},{"number":37,"description":"User clicks on Agregar personas","duration":473,"startTime":"2023-09-28T10:19:39.781-05:00[America/Bogota]","screenshots":[{"screenshot":"c362c5271c3dbceb82e7449a3498b65bb6c83ac2041ec97ffda8c76d394c6968.png","timeStamp":1695914379784},{"screenshot":"8bac7223907446d6dd0278534aebc8f786fe54f808dedfe9c8e5cf68998de27d.png","timeStamp":1695914380254}],"result":"SUCCESS","precondition":false,"level":3},{"number":38,"description":"User clicks on Agregar Adultos","duration":479,"startTime":"2023-09-28T10:19:40.260-05:00[America/Bogota]","screenshots":[{"screenshot":"8bac7223907446d6dd0278534aebc8f786fe54f808dedfe9c8e5cf68998de27d.png","timeStamp":1695914380266},{"screenshot":"03b3159dfd60b23b254e06f62ecbfd665b664ec4d5323948ab00c348bfb8b42d.png","timeStamp":1695914380739}],"result":"SUCCESS","precondition":false,"level":3},{"number":39,"description":"User clicks on Agregar Niños","duration":492,"startTime":"2023-09-28T10:19:40.746-05:00[America/Bogota]","screenshots":[{"screenshot":"03b3159dfd60b23b254e06f62ecbfd665b664ec4d5323948ab00c348bfb8b42d.png","timeStamp":1695914380750},{"screenshot":"1338c2895ac8a848cea57a98201a889ddeb8bd7eae6f97a762861366eb6d3378.png","timeStamp":1695914381238}],"result":"SUCCESS","precondition":false,"level":3},{"number":40,"description":"User clicks on Agregar Niños","duration":441,"startTime":"2023-09-28T10:19:41.245-05:00[America/Bogota]","screenshots":[{"screenshot":"1338c2895ac8a848cea57a98201a889ddeb8bd7eae6f97a762861366eb6d3378.png","timeStamp":1695914381249},{"screenshot":"d422d2651f239fe03807f95a40c2592424a5cef4c3dc211ab1f83498ae925b49.png","timeStamp":1695914381686}],"result":"SUCCESS","precondition":false,"level":3},{"number":41,"description":"User clicks on Escojer Cantidad de habitaciones","duration":438,"startTime":"2023-09-28T10:19:41.692-05:00[America/Bogota]","screenshots":[{"screenshot":"d422d2651f239fe03807f95a40c2592424a5cef4c3dc211ab1f83498ae925b49.png","timeStamp":1695914381697},{"screenshot":"1142c5d3b40be88f1ccc534a56499c77230fda3a2ee3b1ece17d27f8af9f8c01.png","timeStamp":1695914382129}],"result":"SUCCESS","precondition":false,"level":3},{"number":42,"description":"User clicks on Agregar Edad de los niños","duration":500,"startTime":"2023-09-28T10:19:42.135-05:00[America/Bogota]","screenshots":[{"screenshot":"1142c5d3b40be88f1ccc534a56499c77230fda3a2ee3b1ece17d27f8af9f8c01.png","timeStamp":1695914382139},{"screenshot":"8a0e5aabf419c3f0786e5b1e4c95e01884927590b62163c4857eec2dfbc86589.png","timeStamp":1695914382635}],"result":"SUCCESS","precondition":false,"level":3},{"number":43,"description":"User clicks on Escojer Edad del niño 1","duration":425,"startTime":"2023-09-28T10:19:42.640-05:00[America/Bogota]","screenshots":[{"screenshot":"8a0e5aabf419c3f0786e5b1e4c95e01884927590b62163c4857eec2dfbc86589.png","timeStamp":1695914382647},{"screenshot":"84e60a848cdc997da1c6dd93fc76d730d434530c234e336575d85d9469b986a6.png","timeStamp":1695914383065}],"result":"SUCCESS","precondition":false,"level":3},{"number":44,"description":"User clicks on Agregar Edad de los niños","duration":668,"startTime":"2023-09-28T10:19:45.076-05:00[America/Bogota]","screenshots":[{"screenshot":"84e60a848cdc997da1c6dd93fc76d730d434530c234e336575d85d9469b986a6.png","timeStamp":1695914385349},{"screenshot":"0fe9c41c2a1bd7c9db2705dc242e0565ccc5e522525c179eb1e089096b72815f.png","timeStamp":1695914385744}],"result":"SUCCESS","precondition":false,"level":3},{"number":45,"description":"User clicks on Escojer Edad del niño 2","duration":390,"startTime":"2023-09-28T10:19:45.750-05:00[America/Bogota]","screenshots":[{"screenshot":"0fe9c41c2a1bd7c9db2705dc242e0565ccc5e522525c179eb1e089096b72815f.png","timeStamp":1695914385754},{"screenshot":"0fe9c41c2a1bd7c9db2705dc242e0565ccc5e522525c179eb1e089096b72815f.png","timeStamp":1695914386140}],"result":"SUCCESS","precondition":false,"level":3},{"number":46,"description":"User clicks on Boton guardar","duration":2591,"startTime":"2023-09-28T10:19:46.143-05:00[America/Bogota]","screenshots":[{"screenshot":"0fe9c41c2a1bd7c9db2705dc242e0565ccc5e522525c179eb1e089096b72815f.png","timeStamp":1695914386145},{"screenshot":"0fe9c41c2a1bd7c9db2705dc242e0565ccc5e522525c179eb1e089096b72815f.png","htmlSource":"pagesource6822124380237297817.html.txt","timeStamp":1695914388731}],"exception":{"errorType":"org.openqa.selenium.ElementNotInteractableException","message":"element not interactable\n  (Session info: chrome\u003d117.0.5938.92)\nBuild info: version: \u00273.141.59\u0027, revision: \u0027e82be7d358\u0027, time: \u00272018-11-14T08:17:03\u0027\nSystem info: host: \u0027DESKTOP-EBETFGH\u0027, ip: \u0027172.18.1.251\u0027, os.name: \u0027Windows 10\u0027, os.arch: \u0027amd64\u0027, os.version: \u002710.0\u0027, java.version: \u00271.8.0_161\u0027\nDriver info: org.openqa.selenium.chrome.ChromeDriver\nCapabilities {acceptInsecureCerts: false, browserName: chrome, browserVersion: 117.0.5938.92, chrome: {chromedriverVersion: 116.0.5845.96 (1a3918166880..., userDataDir: C:\\Users\\SENA\\AppData\\Local...}, fedcm:accounts: true, goog:chromeOptions: {debuggerAddress: localhost:52167}, javascriptEnabled: true, networkConnectionEnabled: false, pageLoadStrategy: normal, platform: WINDOWS, platformName: WINDOWS, proxy: Proxy(), setWindowRect: true, strictFileInteractability: false, timeouts: {implicit: 0, pageLoad: 300000, script: 30000}, unhandledPromptBehavior: dismiss and notify, webauthn:extension:credBlob: true, webauthn:extension:largeBlob: true, webauthn:extension:minPinLength: true, webauthn:extension:prf: true, webauthn:virtualAuthenticators: true}\nSession ID: 5d4da3f9c927a093206d9dec39cd5db6","stackTrace":[{"declaringClass":"com.co.qvision.tasks.SearchAccommodationTasks","methodName":"performAs","fileName":"SearchAccommodationTasks.java","lineNumber":58},{"declaringClass":"co.com.Senasoft.StepsDefinitions.AccommodationStepDefinition","methodName":"heClicksOnTheAccommodationsOption","fileName":"AccommodationStepDefinition.java","lineNumber":53},{"declaringClass":"cucumber.runner.Runner","methodName":"runPickle","fileName":"Runner.java","lineNumber":80}]},"result":"ERROR","precondition":false,"level":3}]}]}]},{"number":47,"description":"And the search and select one of the results","duration":7,"startTime":"2023-09-28T10:19:48.766-05:00[America/Bogota]","result":"SKIPPED","precondition":false,"level":0},{"number":48,"description":"Then he will have reserved a place of accommodation","duration":5,"startTime":"2023-09-28T10:19:48.775-05:00[America/Bogota]","result":"SKIPPED","precondition":false,"level":0},{"number":49,"description":"Example: {city\u003dBogota}","duration":31255,"startTime":"2023-09-28T10:19:49.516-05:00[America/Bogota]","exception":{"errorType":"org.openqa.selenium.ElementNotInteractableException","message":"element not interactable\n  (Session info: chrome\u003d117.0.5938.92)\nBuild info: version: \u00273.141.59\u0027, revision: \u0027e82be7d358\u0027, time: \u00272018-11-14T08:17:03\u0027\nSystem info: host: \u0027DESKTOP-EBETFGH\u0027, ip: \u0027172.18.1.251\u0027, os.name: \u0027Windows 10\u0027, os.arch: \u0027amd64\u0027, os.version: \u002710.0\u0027, java.version: \u00271.8.0_161\u0027\nDriver info: org.openqa.selenium.chrome.ChromeDriver\nCapabilities {acceptInsecureCerts: false, browserName: chrome, browserVersion: 117.0.5938.92, chrome: {chromedriverVersion: 116.0.5845.96 (1a3918166880..., userDataDir: C:\\Users\\SENA\\AppData\\Local...}, fedcm:accounts: true, goog:chromeOptions: {debuggerAddress: localhost:52248}, javascriptEnabled: true, networkConnectionEnabled: false, pageLoadStrategy: normal, platform: WINDOWS, platformName: WINDOWS, proxy: Proxy(), setWindowRect: true, strictFileInteractability: false, timeouts: {implicit: 0, pageLoad: 300000, script: 30000}, unhandledPromptBehavior: dismiss and notify, webauthn:extension:credBlob: true, webauthn:extension:largeBlob: true, webauthn:extension:minPinLength: true, webauthn:extension:prf: true, webauthn:virtualAuthenticators: true}\nSession ID: 3cb846984c24f1325a36621d959dc67f","stackTrace":[{"declaringClass":"com.co.qvision.tasks.SearchAccommodationTasks","methodName":"performAs","fileName":"SearchAccommodationTasks.java","lineNumber":58},{"declaringClass":"co.com.Senasoft.StepsDefinitions.AccommodationStepDefinition","methodName":"heClicksOnTheAccommodationsOption","fileName":"AccommodationStepDefinition.java","lineNumber":53},{"declaringClass":"cucumber.runner.Runner","methodName":"runPickle","fileName":"Runner.java","lineNumber":80}]},"result":"ERROR","precondition":false,"level":0,"children":[{"number":50,"description":"Given the user Enter the website","duration":19317,"startTime":"2023-09-28T10:19:49.529-05:00[America/Bogota]","screenshots":[{"screenshot":"e6608d6ba5ddd64c6cceec813a8edd3c721ae79b3919ea766fbb4d64fd16e2d9.png","timeStamp":1695914408846}],"result":"SUCCESS","precondition":false,"level":1,"children":[{"number":51,"description":"User opens the https://www.booking.com/","duration":19304,"startTime":"2023-09-28T10:19:49.539-05:00[America/Bogota]","screenshots":[{"screenshot":"e6608d6ba5ddd64c6cceec813a8edd3c721ae79b3919ea766fbb4d64fd16e2d9.png","timeStamp":1695914408843}],"result":"SUCCESS","precondition":false,"level":2}]},{"number":52,"description":"When he clicks on the Accommodations option\r\n| city |\r\n| Bogota |","duration":11921,"startTime":"2023-09-28T10:20:08.847-05:00[America/Bogota]","screenshots":[{"screenshot":"e6608d6ba5ddd64c6cceec813a8edd3c721ae79b3919ea766fbb4d64fd16e2d9.png","timeStamp":1695914408850}],"exception":{"errorType":"org.openqa.selenium.ElementNotInteractableException","message":"element not interactable\n  (Session info: chrome\u003d117.0.5938.92)\nBuild info: version: \u00273.141.59\u0027, revision: \u0027e82be7d358\u0027, time: \u00272018-11-14T08:17:03\u0027\nSystem info: host: \u0027DESKTOP-EBETFGH\u0027, ip: \u0027172.18.1.251\u0027, os.name: \u0027Windows 10\u0027, os.arch: \u0027amd64\u0027, os.version: \u002710.0\u0027, java.version: \u00271.8.0_161\u0027\nDriver info: org.openqa.selenium.chrome.ChromeDriver\nCapabilities {acceptInsecureCerts: false, browserName: chrome, browserVersion: 117.0.5938.92, chrome: {chromedriverVersion: 116.0.5845.96 (1a3918166880..., userDataDir: C:\\Users\\SENA\\AppData\\Local...}, fedcm:accounts: true, goog:chromeOptions: {debuggerAddress: localhost:52248}, javascriptEnabled: true, networkConnectionEnabled: false, pageLoadStrategy: normal, platform: WINDOWS, platformName: WINDOWS, proxy: Proxy(), setWindowRect: true, strictFileInteractability: false, timeouts: {implicit: 0, pageLoad: 300000, script: 30000}, unhandledPromptBehavior: dismiss and notify, webauthn:extension:credBlob: true, webauthn:extension:largeBlob: true, webauthn:extension:minPinLength: true, webauthn:extension:prf: true, webauthn:virtualAuthenticators: true}\nSession ID: 3cb846984c24f1325a36621d959dc67f","stackTrace":[{"declaringClass":"com.co.qvision.tasks.SearchAccommodationTasks","methodName":"performAs","fileName":"SearchAccommodationTasks.java","lineNumber":58},{"declaringClass":"co.com.Senasoft.StepsDefinitions.AccommodationStepDefinition","methodName":"heClicksOnTheAccommodationsOption","fileName":"AccommodationStepDefinition.java","lineNumber":53},{"declaringClass":"cucumber.runner.Runner","methodName":"runPickle","fileName":"Runner.java","lineNumber":80}]},"result":"ERROR","precondition":false,"level":1,"children":[{"number":53,"description":"User close message","duration":1159,"startTime":"2023-09-28T10:20:08.856-05:00[America/Bogota]","screenshots":[{"screenshot":"e6608d6ba5ddd64c6cceec813a8edd3c721ae79b3919ea766fbb4d64fd16e2d9.png","timeStamp":1695914408858},{"screenshot":"1ea256018dc6f0a323ca4a0d8272bc9edcb807861dd730631dd923d5ab3c75d1.png","timeStamp":1695914410015}],"result":"SUCCESS","precondition":false,"level":2,"children":[{"number":54,"description":"User clicks on Ignorar mensaje","duration":1148,"startTime":"2023-09-28T10:20:08.862-05:00[America/Bogota]","screenshots":[{"screenshot":"e6608d6ba5ddd64c6cceec813a8edd3c721ae79b3919ea766fbb4d64fd16e2d9.png","timeStamp":1695914408866},{"screenshot":"1ea256018dc6f0a323ca4a0d8272bc9edcb807861dd730631dd923d5ab3c75d1.png","timeStamp":1695914410010}],"result":"SUCCESS","precondition":false,"level":3}]},{"number":55,"description":"User search accommodation tasks","duration":10743,"startTime":"2023-09-28T10:20:10.019-05:00[America/Bogota]","screenshots":[{"screenshot":"1ea256018dc6f0a323ca4a0d8272bc9edcb807861dd730631dd923d5ab3c75d1.png","timeStamp":1695914410021}],"exception":{"errorType":"org.openqa.selenium.ElementNotInteractableException","message":"element not interactable\n  (Session info: chrome\u003d117.0.5938.92)\nBuild info: version: \u00273.141.59\u0027, revision: \u0027e82be7d358\u0027, time: \u00272018-11-14T08:17:03\u0027\nSystem info: host: \u0027DESKTOP-EBETFGH\u0027, ip: \u0027172.18.1.251\u0027, os.name: \u0027Windows 10\u0027, os.arch: \u0027amd64\u0027, os.version: \u002710.0\u0027, java.version: \u00271.8.0_161\u0027\nDriver info: org.openqa.selenium.chrome.ChromeDriver\nCapabilities {acceptInsecureCerts: false, browserName: chrome, browserVersion: 117.0.5938.92, chrome: {chromedriverVersion: 116.0.5845.96 (1a3918166880..., userDataDir: C:\\Users\\SENA\\AppData\\Local...}, fedcm:accounts: true, goog:chromeOptions: {debuggerAddress: localhost:52248}, javascriptEnabled: true, networkConnectionEnabled: false, pageLoadStrategy: normal, platform: WINDOWS, platformName: WINDOWS, proxy: Proxy(), setWindowRect: true, strictFileInteractability: false, timeouts: {implicit: 0, pageLoad: 300000, script: 30000}, unhandledPromptBehavior: dismiss and notify, webauthn:extension:credBlob: true, webauthn:extension:largeBlob: true, webauthn:extension:minPinLength: true, webauthn:extension:prf: true, webauthn:virtualAuthenticators: true}\nSession ID: 3cb846984c24f1325a36621d959dc67f","stackTrace":[{"declaringClass":"com.co.qvision.tasks.SearchAccommodationTasks","methodName":"performAs","fileName":"SearchAccommodationTasks.java","lineNumber":58},{"declaringClass":"co.com.Senasoft.StepsDefinitions.AccommodationStepDefinition","methodName":"heClicksOnTheAccommodationsOption","fileName":"AccommodationStepDefinition.java","lineNumber":53},{"declaringClass":"cucumber.runner.Runner","methodName":"runPickle","fileName":"Runner.java","lineNumber":80}]},"result":"ERROR","precondition":false,"level":2,"children":[{"number":56,"description":"User enters \u0027Bogota\u0027 into Escribir lugar de hospedaje","duration":480,"startTime":"2023-09-28T10:20:10.026-05:00[America/Bogota]","screenshots":[{"screenshot":"1ea256018dc6f0a323ca4a0d8272bc9edcb807861dd730631dd923d5ab3c75d1.png","timeStamp":1695914410029},{"screenshot":"737829bf5aac909d2394c56d37d80939c41e10f18711294ca2be355a4d520b51.png","timeStamp":1695914410506}],"result":"SUCCESS","precondition":false,"level":3},{"number":57,"description":"User clicks on Añadir fechas de alojamiento","duration":371,"startTime":"2023-09-28T10:20:10.510-05:00[America/Bogota]","screenshots":[{"screenshot":"737829bf5aac909d2394c56d37d80939c41e10f18711294ca2be355a4d520b51.png","timeStamp":1695914410513},{"screenshot":"06f09bdbfa309f16242571e378a3607b1ee0dac84b4f4aac4bd68d1966679591.png","timeStamp":1695914410881}],"result":"SUCCESS","precondition":false,"level":3},{"number":58,"description":"User clicks on Añadir fechas de primer chequeo","duration":321,"startTime":"2023-09-28T10:20:10.885-05:00[America/Bogota]","screenshots":[{"screenshot":"06f09bdbfa309f16242571e378a3607b1ee0dac84b4f4aac4bd68d1966679591.png","timeStamp":1695914410887},{"screenshot":"f6125bb65cd7a1b9ef68b038424dc1ff695fbc6597436a95539f98b2d7a5df50.png","timeStamp":1695914411206}],"result":"SUCCESS","precondition":false,"level":3},{"number":59,"description":"User clicks on Añadir fechas de ultimo chequeo","duration":320,"startTime":"2023-09-28T10:20:11.209-05:00[America/Bogota]","screenshots":[{"screenshot":"f6125bb65cd7a1b9ef68b038424dc1ff695fbc6597436a95539f98b2d7a5df50.png","timeStamp":1695914411211},{"screenshot":"8bc75a5686946ce62700123bdeea9257371a9dca73990544a825fe1203c6adf3.png","timeStamp":1695914411528}],"result":"SUCCESS","precondition":false,"level":3},{"number":60,"description":"User clicks on Añadir fechas de alojamiento","duration":462,"startTime":"2023-09-28T10:20:11.533-05:00[America/Bogota]","screenshots":[{"screenshot":"8bc75a5686946ce62700123bdeea9257371a9dca73990544a825fe1203c6adf3.png","timeStamp":1695914411537},{"screenshot":"e08d5b72bf9dcba6286fd0d259df2a7c147b81319782a334bc166e9dfd10cffe.png","timeStamp":1695914411995}],"result":"SUCCESS","precondition":false,"level":3},{"number":61,"description":"User clicks on Agregar personas","duration":380,"startTime":"2023-09-28T10:20:12.001-05:00[America/Bogota]","screenshots":[{"screenshot":"e08d5b72bf9dcba6286fd0d259df2a7c147b81319782a334bc166e9dfd10cffe.png","timeStamp":1695914412007},{"screenshot":"dd0a31c297c339a01ba13881aa87100b07619f0552ca110e81d692537389bbda.png","timeStamp":1695914412381}],"result":"SUCCESS","precondition":false,"level":3},{"number":62,"description":"User clicks on Agregar Adultos","duration":392,"startTime":"2023-09-28T10:20:12.384-05:00[America/Bogota]","screenshots":[{"screenshot":"dd0a31c297c339a01ba13881aa87100b07619f0552ca110e81d692537389bbda.png","timeStamp":1695914412386},{"screenshot":"1e85cb1dde70988a2862a8238ab23cc956cec7d72ecc46d3c62d30a5dc949c2b.png","timeStamp":1695914412776}],"result":"SUCCESS","precondition":false,"level":3},{"number":63,"description":"User clicks on Agregar Niños","duration":443,"startTime":"2023-09-28T10:20:12.781-05:00[America/Bogota]","screenshots":[{"screenshot":"1e85cb1dde70988a2862a8238ab23cc956cec7d72ecc46d3c62d30a5dc949c2b.png","timeStamp":1695914412785},{"screenshot":"69873a3a644106c74cddf2cc74a4902c1db76b4d37b4bb22c3a0aa09a4634e34.png","timeStamp":1695914413223}],"result":"SUCCESS","precondition":false,"level":3},{"number":64,"description":"User clicks on Agregar Niños","duration":407,"startTime":"2023-09-28T10:20:13.229-05:00[America/Bogota]","screenshots":[{"screenshot":"69873a3a644106c74cddf2cc74a4902c1db76b4d37b4bb22c3a0aa09a4634e34.png","timeStamp":1695914413233},{"screenshot":"b1fe8e36b5571c89a7dfd6310018acb09bffb5cb44ec62f4d5f4208b6620ea15.png","timeStamp":1695914413636}],"result":"SUCCESS","precondition":false,"level":3},{"number":65,"description":"User clicks on Escojer Cantidad de habitaciones","duration":409,"startTime":"2023-09-28T10:20:13.642-05:00[America/Bogota]","screenshots":[{"screenshot":"b1fe8e36b5571c89a7dfd6310018acb09bffb5cb44ec62f4d5f4208b6620ea15.png","timeStamp":1695914413645},{"screenshot":"316dc0c0ce6cd23d0a9ec08c3f8744fa75bc9557869e4515b4c0e61628ecab12.png","timeStamp":1695914414050}],"result":"SUCCESS","precondition":false,"level":3},{"number":66,"description":"User clicks on Agregar Edad de los niños","duration":517,"startTime":"2023-09-28T10:20:14.055-05:00[America/Bogota]","screenshots":[{"screenshot":"316dc0c0ce6cd23d0a9ec08c3f8744fa75bc9557869e4515b4c0e61628ecab12.png","timeStamp":1695914414060},{"screenshot":"0ddb18cefc68615213bba5545fec088b0d1a3bb6eee6fd2e8333e2cb5d7a37fc.png","timeStamp":1695914414571}],"result":"SUCCESS","precondition":false,"level":3},{"number":67,"description":"User clicks on Escojer Edad del niño 1","duration":460,"startTime":"2023-09-28T10:20:14.578-05:00[America/Bogota]","screenshots":[{"screenshot":"0ddb18cefc68615213bba5545fec088b0d1a3bb6eee6fd2e8333e2cb5d7a37fc.png","timeStamp":1695914414583},{"screenshot":"5b8d7f7dc9c455815117e3b7d3d3273b4e243c32d78510ae79391614441cfce5.png","timeStamp":1695914415038}],"result":"SUCCESS","precondition":false,"level":3},{"number":68,"description":"User clicks on Agregar Edad de los niños","duration":693,"startTime":"2023-09-28T10:20:17.057-05:00[America/Bogota]","screenshots":[{"screenshot":"5b8d7f7dc9c455815117e3b7d3d3273b4e243c32d78510ae79391614441cfce5.png","timeStamp":1695914417257},{"screenshot":"fb1286d838189a508e1dc117bce9363c1e60a73d73a4aa645e6e845424ecab5b.png","timeStamp":1695914417750}],"result":"SUCCESS","precondition":false,"level":3},{"number":69,"description":"User clicks on Escojer Edad del niño 2","duration":409,"startTime":"2023-09-28T10:20:17.755-05:00[America/Bogota]","screenshots":[{"screenshot":"fb1286d838189a508e1dc117bce9363c1e60a73d73a4aa645e6e845424ecab5b.png","timeStamp":1695914417759},{"screenshot":"fb1286d838189a508e1dc117bce9363c1e60a73d73a4aa645e6e845424ecab5b.png","timeStamp":1695914418164}],"result":"SUCCESS","precondition":false,"level":3},{"number":70,"description":"User clicks on Boton guardar","duration":2591,"startTime":"2023-09-28T10:20:18.167-05:00[America/Bogota]","screenshots":[{"screenshot":"fb1286d838189a508e1dc117bce9363c1e60a73d73a4aa645e6e845424ecab5b.png","timeStamp":1695914418169},{"screenshot":"fb1286d838189a508e1dc117bce9363c1e60a73d73a4aa645e6e845424ecab5b.png","htmlSource":"pagesource9134169258406413314.html.txt","timeStamp":1695914420755}],"exception":{"errorType":"org.openqa.selenium.ElementNotInteractableException","message":"element not interactable\n  (Session info: chrome\u003d117.0.5938.92)\nBuild info: version: \u00273.141.59\u0027, revision: \u0027e82be7d358\u0027, time: \u00272018-11-14T08:17:03\u0027\nSystem info: host: \u0027DESKTOP-EBETFGH\u0027, ip: \u0027172.18.1.251\u0027, os.name: \u0027Windows 10\u0027, os.arch: \u0027amd64\u0027, os.version: \u002710.0\u0027, java.version: \u00271.8.0_161\u0027\nDriver info: org.openqa.selenium.chrome.ChromeDriver\nCapabilities {acceptInsecureCerts: false, browserName: chrome, browserVersion: 117.0.5938.92, chrome: {chromedriverVersion: 116.0.5845.96 (1a3918166880..., userDataDir: C:\\Users\\SENA\\AppData\\Local...}, fedcm:accounts: true, goog:chromeOptions: {debuggerAddress: localhost:52248}, javascriptEnabled: true, networkConnectionEnabled: false, pageLoadStrategy: normal, platform: WINDOWS, platformName: WINDOWS, proxy: Proxy(), setWindowRect: true, strictFileInteractability: false, timeouts: {implicit: 0, pageLoad: 300000, script: 30000}, unhandledPromptBehavior: dismiss and notify, webauthn:extension:credBlob: true, webauthn:extension:largeBlob: true, webauthn:extension:minPinLength: true, webauthn:extension:prf: true, webauthn:virtualAuthenticators: true}\nSession ID: 3cb846984c24f1325a36621d959dc67f","stackTrace":[{"declaringClass":"com.co.qvision.tasks.SearchAccommodationTasks","methodName":"performAs","fileName":"SearchAccommodationTasks.java","lineNumber":58},{"declaringClass":"co.com.Senasoft.StepsDefinitions.AccommodationStepDefinition","methodName":"heClicksOnTheAccommodationsOption","fileName":"AccommodationStepDefinition.java","lineNumber":53},{"declaringClass":"cucumber.runner.Runner","methodName":"runPickle","fileName":"Runner.java","lineNumber":80}]},"result":"ERROR","precondition":false,"level":3}]}]}]},{"number":71,"description":"And the search and select one of the results","duration":4,"startTime":"2023-09-28T10:20:20.784-05:00[America/Bogota]","result":"SKIPPED","precondition":false,"level":0},{"number":72,"description":"Then he will have reserved a place of accommodation","duration":4,"startTime":"2023-09-28T10:20:20.789-05:00[America/Bogota]","result":"SKIPPED","precondition":false,"level":0}],"userStory":{"id":"accommodation","storyName":"Accommodation","path":"src/test/resources/features/accommodation.feature","narrative":"  I need to perform actions in the Accommodation module","type":"feature"},"featureTag":{"name":"Features/Accommodation","type":"feature","displayName":"Features/Accommodation"},"title":"Book a successful accommodation","backgroundTitle":"","backgroundDescription":"","tags":[{"name":"Reservationbysearch","type":"tag","displayName":"Reservationbysearch"}],"startTime":"2023-09-28T10:18:48.174-05:00[America/Bogota]","duration":42204,"testFailureCause":{"errorType":"org.openqa.selenium.ElementNotInteractableException","message":"element not interactable\n  (Session info: chrome\u003d117.0.5938.92)\nBuild info: version: \u00273.141.59\u0027, revision: \u0027e82be7d358\u0027, time: \u00272018-11-14T08:17:03\u0027\nSystem info: host: \u0027DESKTOP-EBETFGH\u0027, ip: \u0027172.18.1.251\u0027, os.name: \u0027Windows 10\u0027, os.arch: \u0027amd64\u0027, os.version: \u002710.0\u0027, java.version: \u00271.8.0_161\u0027\nDriver info: org.openqa.selenium.chrome.ChromeDriver\nCapabilities {acceptInsecureCerts: false, browserName: chrome, browserVersion: 117.0.5938.92, chrome: {chromedriverVersion: 116.0.5845.96 (1a3918166880..., userDataDir: C:\\Users\\SENA\\AppData\\Local...}, fedcm:accounts: true, goog:chromeOptions: {debuggerAddress: localhost:52248}, javascriptEnabled: true, networkConnectionEnabled: false, pageLoadStrategy: normal, platform: WINDOWS, platformName: WINDOWS, proxy: Proxy(), setWindowRect: true, strictFileInteractability: false, timeouts: {implicit: 0, pageLoad: 300000, script: 30000}, unhandledPromptBehavior: dismiss and notify, webauthn:extension:credBlob: true, webauthn:extension:largeBlob: true, webauthn:extension:minPinLength: true, webauthn:extension:prf: true, webauthn:virtualAuthenticators: true}\nSession ID: 3cb846984c24f1325a36621d959dc67f","stackTrace":[{"declaringClass":"com.co.qvision.tasks.SearchAccommodationTasks","methodName":"performAs","fileName":"SearchAccommodationTasks.java","lineNumber":58},{"declaringClass":"co.com.Senasoft.StepsDefinitions.AccommodationStepDefinition","methodName":"heClicksOnTheAccommodationsOption","fileName":"AccommodationStepDefinition.java","lineNumber":53},{"declaringClass":"✽","methodName":"he clicks on the Accommodations option","fileName":"src/test/resources/features/accommodation.feature","lineNumber":9}]},"testFailureClassname":"org.openqa.selenium.ElementNotInteractableException","testFailureMessage":"element not interactable\n  (Session info: chrome\u003d117.0.5938.92)\nBuild info: version: \u00273.141.59\u0027, revision: \u0027e82be7d358\u0027, time: \u00272018-11-14T08:17:03\u0027\nSystem info: host: \u0027DESKTOP-EBETFGH\u0027, ip: \u0027172.18.1.251\u0027, os.name: \u0027Windows 10\u0027, os.arch: \u0027amd64\u0027, os.version: \u002710.0\u0027, java.version: \u00271.8.0_161\u0027\nDriver info: org.openqa.selenium.chrome.ChromeDriver\nCapabilities {acceptInsecureCerts: false, browserName: chrome, browserVersion: 117.0.5938.92, chrome: {chromedriverVersion: 116.0.5845.96 (1a3918166880..., userDataDir: C:\\Users\\SENA\\AppData\\Local...}, fedcm:accounts: true, goog:chromeOptions: {debuggerAddress: localhost:52248}, javascriptEnabled: true, networkConnectionEnabled: false, pageLoadStrategy: normal, platform: WINDOWS, platformName: WINDOWS, proxy: Proxy(), setWindowRect: true, strictFileInteractability: false, timeouts: {implicit: 0, pageLoad: 300000, script: 30000}, unhandledPromptBehavior: dismiss and notify, webauthn:extension:credBlob: true, webauthn:extension:largeBlob: true, webauthn:extension:minPinLength: true, webauthn:extension:prf: true, webauthn:virtualAuthenticators: true}\nSession ID: 3cb846984c24f1325a36621d959dc67f","testFailureSummary":"ERROR;org.openqa.selenium.ElementNotInteractableException;element not interactable\n  (Session info: chrome\u003d117.0.5938.92)\nBuild info: version: \u00273.141.59\u0027, revision: \u0027e82be7d358\u0027, time: \u00272018-11-14T08:17:03\u0027\nSystem info: host: \u0027DESKTOP-EBETFGH\u0027, ip: \u0027172.18.1.251\u0027, os.name: \u0027Windows 10\u0027, os.arch: \u0027amd64\u0027, os.version: \u002710.0\u0027, java.version: \u00271.8.0_161\u0027\nDriver info: org.openqa.selenium.chrome.ChromeDriver\nCapabilities {acceptInsecureCerts: false, browserName: chrome, browserVersion: 117.0.5938.92, chrome: {chromedriverVersion: 116.0.5845.96 (1a3918166880..., userDataDir: C:\\Users\\SENA\\AppData\\Local...}, fedcm:accounts: true, goog:chromeOptions: {debuggerAddress: localhost:52248}, javascriptEnabled: true, networkConnectionEnabled: false, pageLoadStrategy: normal, platform: WINDOWS, platformName: WINDOWS, proxy: Proxy(), setWindowRect: true, strictFileInteractability: false, timeouts: {implicit: 0, pageLoad: 300000, script: 30000}, unhandledPromptBehavior: dismiss and notify, webauthn:extension:credBlob: true, webauthn:extension:largeBlob: true, webauthn:extension:minPinLength: true, webauthn:extension:prf: true, webauthn:virtualAuthenticators: true}\nSession ID: 3cb846984c24f1325a36621d959dc67f;SearchAccommodationTasks.java","projectKey":"","annotatedResult":"ERROR","isManualTestingUpToDate":false,"dataTable":{"headers":["city"],"rows":[{"values":["Popayan"],"result":"ERROR"},{"values":["Cali"],"result":"ERROR"},{"values":["Bogota"],"result":"ERROR"}],"predefinedRows":true,"scenarioOutline":"When he clicks on the Accommodations option\n\rAnd the search and select one of the results\n\rThen he will have reserved a place of accommodation\n\r","dataSetDescriptors":[{"startRow":0,"rowCount":0,"name":""}]},"manual":false,"testSource":"Cucumber","actors":[{"name":"User","can":["browse the web"]}],"result":"ERROR","scenarioOutline":"When he clicks on the Accommodations option\r\n|city|\r\n|\u003ccity\u003e|\r\nAnd the search and select one of the results\r\nThen he will have reserved a place of accommodation"}